{
    "Features.ClayForming.ModMenu.lblInstantComplete.HoverText":  "กําหนดว่าจะทําสูตรปัจจุบันให้เสร็จทันทีหรือไม่",
    "Features.ClayForming.VoxelsPerClick":  "{0} Voxels ต่อคลิก: {1}",
    "Features.ModMenu.ClayForming.TabName":  "การขึ้นรูปดินเหนียว",
    "Features.ClayForming.ModMenu.lblInstantComplete.Text":  "เสร็จสมบูรณ์ทันที",
    "Features.ClayForming.Description":  "จัดการการตั้งค่าการขึ้นรูปดินเหนียว",
    "Features.ClayForming.ModMenu.lblVoxelsPerClick.HoverText":  "กําหนดจํานวนว็อกเซลที่จัดการในคราวเดียวเมื่อสร้างดินเหนียว",
    "Features.ClayForming.ModMenu.lblTitle.Text":  "การตั้งค่าการขึ้นรูปดินเหนียว",
    "Features.ClayForming.ModMenu.intVoxelsPerClick.Unit-singular":  "วอกเซล",
    "Features.ClayForming.ModMenu.lblVoxelsPerClick.Text":  "Voxels ต่อคลิก",
    "Features.ClayForming.InstantComplete.Description":  "เปลี่ยนว่ารายการงานควรเสร็จสมบูรณ์ทันทีหรือไม่เมื่อใช้งาน จริงหรือเท็จ ค่าเริ่มต้น: เท็จ",
    "Features.ClayForming.ModMenu.lblDescription.Text":  "ให้วิธีที่ง่ายขึ้นสําหรับผู้เล่นในการสร้างไอเท็มดินเหนียวภายในเกม",
    "Features.ClayForming.VoxelsPerClick.Description":  "เปลี่ยนจํานวน voxel ที่ย้ายต่อคลิก ต่ําสุด: 1, สูงสุด: 8, ค่าเริ่มต้น: 1.",
    "Features.ClayForming.ModMenu.TabName":  "การขึ้นรูปดินเหนียว",
    "Features.ClayForming.ClayRequired":  "ดินเหนียวทั้งหมดที่ต้องการ: {0}",
    "Features.ClayForming.ModMenu.intVoxelsPerClick.Unit-plural":  "ว็อกเซล",
    "Features.ClayForming.InstantComplete":  "{0} เสร็จสมบูรณ์ทันที: {1}"
}
